hwcomponents_neurosim/__init__.py
hwcomponents_neurosim/_version.py
hwcomponents_neurosim/default_config.cfg
hwcomponents_neurosim/main.py
hwcomponents_neurosim/neurointerface.py
hwcomponents_neurosim/DNN_NeuroSim_V1.3/.git
hwcomponents_neurosim/DNN_NeuroSim_V1.3/README.md
hwcomponents_neurosim/DNN_NeuroSim_V1.3/Documents/DNN NeuroSim V1.3 Manual.pdf
hwcomponents_neurosim/DNN_NeuroSim_V1.3/Inference_pytorch/__init__.py
hwcomponents_neurosim/DNN_NeuroSim_V1.3/Inference_pytorch/inference.py
hwcomponents_neurosim/DNN_NeuroSim_V1.3/Inference_pytorch/train.py
hwcomponents_neurosim/DNN_NeuroSim_V1.3/Inference_pytorch/NeuroSIM/Adder.cpp
hwcomponents_neurosim/DNN_NeuroSim_V1.3/Inference_pytorch/NeuroSIM/Adder.h
hwcomponents_neurosim/DNN_NeuroSim_V1.3/Inference_pytorch/NeuroSIM/AdderTree.cpp
hwcomponents_neurosim/DNN_NeuroSim_V1.3/Inference_pytorch/NeuroSIM/AdderTree.h
hwcomponents_neurosim/DNN_NeuroSim_V1.3/Inference_pytorch/NeuroSIM/BitShifter.cpp
hwcomponents_neurosim/DNN_NeuroSim_V1.3/Inference_pytorch/NeuroSIM/BitShifter.h
hwcomponents_neurosim/DNN_NeuroSim_V1.3/Inference_pytorch/NeuroSIM/Buffer.cpp
hwcomponents_neurosim/DNN_NeuroSim_V1.3/Inference_pytorch/NeuroSIM/Buffer.h
hwcomponents_neurosim/DNN_NeuroSim_V1.3/Inference_pytorch/NeuroSIM/Bus.cpp
hwcomponents_neurosim/DNN_NeuroSim_V1.3/Inference_pytorch/NeuroSIM/Bus.h
hwcomponents_neurosim/DNN_NeuroSim_V1.3/Inference_pytorch/NeuroSIM/Chip.cpp
hwcomponents_neurosim/DNN_NeuroSim_V1.3/Inference_pytorch/NeuroSIM/Chip.h
hwcomponents_neurosim/DNN_NeuroSim_V1.3/Inference_pytorch/NeuroSIM/Comparator.cpp
hwcomponents_neurosim/DNN_NeuroSim_V1.3/Inference_pytorch/NeuroSIM/Comparator.h
hwcomponents_neurosim/DNN_NeuroSim_V1.3/Inference_pytorch/NeuroSIM/CurrentSenseAmp.cpp
hwcomponents_neurosim/DNN_NeuroSim_V1.3/Inference_pytorch/NeuroSIM/CurrentSenseAmp.h
hwcomponents_neurosim/DNN_NeuroSim_V1.3/Inference_pytorch/NeuroSIM/DFF.cpp
hwcomponents_neurosim/DNN_NeuroSim_V1.3/Inference_pytorch/NeuroSIM/DFF.h
hwcomponents_neurosim-1.0.27.dist-info/METADATA
hwcomponents_neurosim-1.0.27.dist-info/WHEEL
hwcomponents_neurosim-1.0.27.dist-info/top_level.txt
hwcomponents_neurosim-1.0.27.dist-info/RECORD
