Metadata-Version: 2.4
Name: hwcomponents-neurosim
Version: 1.0.27
Summary: A package for estimating the energy and area of NeuroSim components
Author-email: Tanner Andrulis <andrulis@mit.edu>
License-Expression: MIT
Keywords: hardware,energy,estimation,analog,adc,neurosim,pim,processing-in-memory,cim
Classifier: Development Status :: 3 - Alpha
Classifier: Programming Language :: Python :: 3
Classifier: Topic :: Scientific/Engineering :: Electronic Design Automation (EDA)
Requires-Python: >=3.12
Requires-Dist: hwcomponents
